mr_studydev-1.0.0.dist-info/licenses/LICENSE
studydev/__init__.py
studydev/main.py
studydev/core/__init__.py
studydev/core/config.py
studydev/core/database.py
studydev/modules/__init__.py
studydev/modules/project/__init__.py
studydev/modules/project/commands.py
studydev/modules/project/manager.py
studydev/modules/session/__init__.py
studydev/modules/session/commands.py
studydev/modules/session/manager.py
studydev/modules/study/__init__.py
studydev/modules/study/commands.py
studydev/modules/study/manager.py
studydev/utils/__init__.py
studydev/utils/integration.py
studydev/utils/interactive.py
mr_studydev-1.0.0.dist-info/METADATA
mr_studydev-1.0.0.dist-info/WHEEL
mr_studydev-1.0.0.dist-info/entry_points.txt
mr_studydev-1.0.0.dist-info/top_level.txt
mr_studydev-1.0.0.dist-info/RECORD
