Metadata-Version: 2.4
Name: mr-studydev
Version: 1.0.0
Summary: 🎯 Ultimate Student & Developer Productivity CLI Tool with Pomodoro, Projects & Study Materials
Home-page: https://github.com/the-ai-developer/mr.studydev
Author: PrinceTheProgrammer
Author-email: PrinceTheProgrammer <princetheprogrammer@example.com>
License: MIT License
Project-URL: Homepage, https://github.com/the-ai-developer/mr.studydev
Project-URL: Bug Reports, https://github.com/the-ai-developer/mr.studydev/issues
Project-URL: Source, https://github.com/the-ai-developer/mr.studydev
Project-URL: Documentation, https://github.com/the-ai-developer/mr.studydev#readme
Keywords: productivity,pomodoro,cli,study,project-management,flashcards,terminal,developer-tools,student-tools,time-management
Classifier: Development Status :: 5 - Production/Stable
Classifier: Environment :: Console
Classifier: Intended Audience :: Developers
Classifier: Intended Audience :: Education
Classifier: Intended Audience :: End Users/Desktop
Classifier: License :: OSI Approved :: MIT License
Classifier: Natural Language :: English
Classifier: Operating System :: OS Independent
Classifier: Programming Language :: Python :: 3
Classifier: Programming Language :: Python :: 3.8
Classifier: Programming Language :: Python :: 3.9
Classifier: Programming Language :: Python :: 3.10
Classifier: Programming Language :: Python :: 3.11
Classifier: Programming Language :: Python :: 3.12
Classifier: Topic :: Education
Classifier: Topic :: Office/Business :: Scheduling
Classifier: Topic :: Software Development
Classifier: Topic :: System :: Shells
Classifier: Topic :: Terminals
Classifier: Topic :: Utilities
Requires-Python: >=3.8
License-File: LICENSE
Requires-Dist: click>=8.0.0
Requires-Dist: rich>=13.0.0
Requires-Dist: typer>=0.9.0
Requires-Dist: json5>=0.9.0
Requires-Dist: pyyaml>=6.0
Requires-Dist: python-dateutil>=2.8.0
Requires-Dist: arrow>=1.2.0
Provides-Extra: dev
Requires-Dist: pytest>=7.4.0; extra == "dev"
Requires-Dist: pytest-cov>=4.1.0; extra == "dev"
Requires-Dist: black>=23.0.0; extra == "dev"
Requires-Dist: flake8>=6.0.0; extra == "dev"
Dynamic: author
Dynamic: home-page
Dynamic: license-file
Dynamic: requires-python
